read_OU_mtx/__init__.py
read_OU_mtx-0.0.2.dist-info/METADATA
read_OU_mtx-0.0.2.dist-info/WHEEL
read_OU_mtx-0.0.2.dist-info/top_level.txt
read_OU_mtx-0.0.2.dist-info/RECORD
