Metadata-Version: 2.1
Name: read-OU-mtx
Version: 0.0.2
Summary: read single cell raw data in C4 platform .
Home-page: https://github.com/wangzichenbioinformatics/read_ou_mtx/
Author: Wangchen
Author-email: wch_bioinformatics@163.com
License: UNKNOWN
Platform: UNKNOWN
Classifier: Programming Language :: Python :: 3
Classifier: License :: OSI Approved :: MIT License
Classifier: Operating System :: OS Independent
Requires-Python: >=3.9
